airports/__init__.py
airports/airports.py
airports/merge.py
airports/data/airports.json
airports-0.1.2.dist-info/METADATA
airports-0.1.2.dist-info/WHEEL
airports-0.1.2.dist-info/licenses/LICENSE.txt
airports-0.1.2.dist-info/RECORD
