Metadata-Version: 2.4
Name: airports
Version: 0.1.2
Summary: A comprehensive Python library for airport data management and querying heavily influenced by Tim Rogers' Airports gem. This library provides fast, efficient lookups for airport information using IATA codes, ICAO codes, cities, regions, and countries.
Project-URL: Homepage, https://github.com/berubejd/airports
Project-URL: Bug Tracker, https://github.com/berubejd/airports/issues
Project-URL: Source Code, https://github.com/berubejd/airports
Author-email: Jeffrey Berube <berubejd@gmail.com>
License: MIT License
License-File: LICENSE.txt
Keywords: airports,aviation,travel
Classifier: Development Status :: 3 - Alpha
Classifier: Intended Audience :: Developers
Classifier: License :: OSI Approved :: MIT License
Classifier: Programming Language :: Python :: 3
Classifier: Programming Language :: Python :: 3.7
Classifier: Programming Language :: Python :: 3.8
Classifier: Programming Language :: Python :: 3.9
Classifier: Programming Language :: Python :: 3.10
Classifier: Programming Language :: Python :: 3.11
Classifier: Topic :: Software Development :: Libraries :: Python Modules
Requires-Python: >=3.7
Provides-Extra: dev
Requires-Dist: black>=22.0.0; extra == 'dev'
Requires-Dist: build>=0.10.0; extra == 'dev'
Requires-Dist: flake8>=4.0.0; extra == 'dev'
Requires-Dist: isort>=5.0.0; extra == 'dev'
Requires-Dist: pytest-cov>=4.0.0; extra == 'dev'
Requires-Dist: pytest>=7.0.0; extra == 'dev'
Requires-Dist: twine>=4.0.0; extra == 'dev'
